{"id":430,"name":"Honchkrow","types":["dark","flying"],"gen":4,"statTotal":505,"legendary":false,"genus":"Big Boss","mythical":false,"stats":{"hp":100,"atk":125,"def":52,"spa":105,"spd":52,"spe":71},"height":0.9,"weight":27.3,"abilities":[{"name":"Insomnia","isHidden":false},{"name":"Super Luck","isHidden":false},{"name":"Moxie","isHidden":true}],"flavor":"One cry from this Pokémon, and a murder of Murkrow come flying. At such times, one would think the curtain of night had fallen, plunging the world into jet-black darkness."}
